pyrarchical/__init__.py
pyrarchical/diagram.py
pyrarchical/hsm.py
pyrarchical/examples/__init__.py
pyrarchical/examples/canonical.py
pyrarchical/examples/canonical.txt
pyrarchical/examples/cd_player.py
pyrarchical/examples/cd_player.txt
pyrarchical/examples/orthogonal.py
pyrarchical/examples/orthogonal.txt
pyrarchical-0.8.0.dist-info/METADATA
pyrarchical-0.8.0.dist-info/WHEEL
pyrarchical-0.8.0.dist-info/licenses/LICENSE
pyrarchical-0.8.0.dist-info/RECORD
