Metadata-Version: 2.4
Name: pyrarchical
Version: 0.8.0
Summary: A framework for a responsive heirarchical state-machine
Project-URL: Homepage, https://gitlab.com/nealtanner/pyrarchical-state-machine
Project-URL: Issues, https://gitlab.com/nealtanner/pyrarchical-state-machine/-/issues
Author: Matt Roelle, Neal Tanner, Teresa Gadda
License-File: LICENSE
Classifier: License :: OSI Approved :: MIT License
Classifier: Operating System :: OS Independent
Classifier: Programming Language :: Python :: 3
Requires-Python: >=3.8
